sirji_messages/__init__.py
sirji_messages/action_enum.py
sirji_messages/agent_enum.py
sirji_messages/custom_exceptions.py
sirji_messages/helper.py
sirji_messages/parser.py
sirji_messages/permissions.py
sirji_messages/messages/__init__.py
sirji_messages/messages/factory.py
sirji_messages/messages/actions/__init__.py
sirji_messages/messages/actions/base.py
sirji_messages/messages/actions/create_assistant.py
sirji_messages/messages/actions/create_project_file.py
sirji_messages/messages/actions/do_nothing.py
sirji_messages/messages/actions/execute_command.py
sirji_messages/messages/actions/extract_dependencies.py
sirji_messages/messages/actions/fetch_recipe.py
sirji_messages/messages/actions/fetch_recipe_index.py
sirji_messages/messages/actions/find_and_replace.py
sirji_messages/messages/actions/infer.py
sirji_messages/messages/actions/infer_in_existing_thread.py
sirji_messages/messages/actions/insert_above.py
sirji_messages/messages/actions/insert_below.py
sirji_messages/messages/actions/invoke_agent.py
sirji_messages/messages/actions/invoke_agent_existing_session.py
sirji_messages/messages/actions/log_steps.py
sirji_messages/messages/actions/question.py
sirji_messages/messages/actions/read_agent_output_files.py
sirji_messages/messages/actions/read_agent_output_index.py
sirji_messages/messages/actions/read_project_files.py
sirji_messages/messages/actions/response.py
sirji_messages/messages/actions/run_server.py
sirji_messages/messages/actions/search_code_in_project.py
sirji_messages/messages/actions/search_file_in_project.py
sirji_messages/messages/actions/solution_complete.py
sirji_messages/messages/actions/store_in_agent_output.py
sirji_messages/messages/actions/store_in_scratch_pad.py
sirji_messages/messages/actions/sync_codebase.py
sirji_messages/messages/actions/train_using_search_term.py
sirji_messages/messages/actions/train_using_url.py
tests/__init__.py
tests/test_action_enum.py
tests/test_agent_enum.py
tests/test_base.py
tests/test_create_project_file.py
sirji_messages-0.0.34.dist-info/LICENSE
sirji_messages-0.0.34.dist-info/METADATA
sirji_messages-0.0.34.dist-info/WHEEL
sirji_messages-0.0.34.dist-info/top_level.txt
sirji_messages-0.0.34.dist-info/RECORD
