Metadata-Version: 2.1
Name: sirji-messages
Version: 0.0.34
Summary: Sirji messaging protocol implementation to create, validate and parse messages.
Home-page: https://github.com/sirji-ai/sirji
Author: Sirji
License: MIT
Requires-Python: >=3.6
License-File: LICENSE
